jiophone-video/__init__.py
jiophone-video/convert.py
jiophone-video/main.py
jiophone_video/__init__.py
jiophone_video/main.py
jiophone_video-1.5.dist-info/DESCRIPTION.rst
jiophone_video-1.5.dist-info/METADATA
jiophone_video-1.5.dist-info/RECORD
jiophone_video-1.5.dist-info/WHEEL
jiophone_video-1.5.dist-info/entry_points.txt
jiophone_video-1.5.dist-info/metadata.json
jiophone_video-1.5.dist-info/top_level.txt
