Metadata-Version: 2.0
Name: jiophone-video
Version: 1.5
Summary: Convert video to JioPhone compatible
Home-page: https://github.com/Hritik14/jiophone-video
Author: Hritik Vijay
Author-email: Hritikxx8@gmail.com
License: BSD
Keywords: Jio,Jio Phone,Video
Platform: UNKNOWN
Requires-Dist: ffmpy
